pyemerald/__init__.py
pyemerald/codec.py
pyemerald/constants.py
pyemerald/game.py
pyemerald/items.py
pyemerald/level.py
pyemerald/moves.py
pyemerald/nature_stats.py
pyemerald/pokemon.py
pyemerald/pokemon_info.py
pyemerald/raw_section.py
pyemerald/save.py
pyemerald/section.py
pyemerald/utils.py
pyemerald-0.5.2.dist-info/LICENSE.txt
pyemerald-0.5.2.dist-info/WHEEL
pyemerald-0.5.2.dist-info/METADATA
pyemerald-0.5.2.dist-info/RECORD
