Metadata-Version: 2.1
Name: pyemerald
Version: 0.5.2
Summary: A package to modify save files from Pokemon Emerald
Home-page: https://gitlab.com/magnetos_son/pyemerald
License: MIT
Author: matkvist
Author-email: kvistanalytics@gmail.com
Requires-Python: >=3.8,<4.0
Classifier: License :: OSI Approved :: MIT License
Classifier: Programming Language :: Python :: 3
Classifier: Programming Language :: Python :: 3.10
Classifier: Programming Language :: Python :: 3.8
Classifier: Programming Language :: Python :: 3.9
Project-URL: Repository, https://gitlab.com/magnetos_son/pyemerald
